sidex/__init__.py
sidex/client.py
sidex/dump.py
sidex/request.py
sidex/server.py
sidex/setup.py
sidex-1.5.dist-info/METADATA
sidex-1.5.dist-info/WHEEL
sidex-1.5.dist-info/top_level.txt
sidex-1.5.dist-info/RECORD
