Metadata-Version: 2.1
Name: sidex
Version: 1.5
Summary: SIDEX: Simple Data Exchange server over HTTP
Home-page: https://bitbucket.org/ryou_ohsawa/sidex/src/master/
Author: Ryou Ohsawa
Author-email: ohsawa@ioa.s.u-tokyo.ac.jp
Maintainer: Ryou Ohsawa
Maintainer-email: ohsawa@ioa.s.u-tokyo.ac.jp
License: MIT
Platform: UNKNOWN
Classifier: Development Status :: 3 - Alpha
Classifier: Environment :: Console
Classifier: Intended Audience :: Science/Research
Classifier: License :: OSI Approved :: MIT License
Classifier: Operating System :: POSIX :: Linux
Classifier: Programming Language :: Python :: 3
Classifier: Programming Language :: Python :: 3.7
Requires-Dist: flask (>=2.0)
Requires-Dist: requests (>=2.27)
